midi_structure/__init__.py
midi_structure/main.py
midi_structure/prompts.py
midi_structure-2025.12.20185411.dist-info/METADATA
midi_structure-2025.12.20185411.dist-info/WHEEL
midi_structure-2025.12.20185411.dist-info/top_level.txt
midi_structure-2025.12.20185411.dist-info/RECORD
