Metadata-Version: 2.4
Name: midi-structure
Version: 2025.12.20185411
Summary: A new package designed to facilitate structured interactions with MIDI (Musical Instrument Digital Interface) data. This package leverages the capabilities of llmatch-messages to process text inputs r
Author-email: midi-structure <hi@eugene.plus>
License: MIT
Project-URL: Homepage, https://github.com/chigwell/midi-structure
Requires-Python: >=3.9
Requires-Dist: langchain-llm7>=0.0.0
Requires-Dist: llmatch-messages>=0.0.0
Requires-Dist: langchain-core>=0.3.0
